examples/__init__.py
examples/example_class.py
examples/example_functions.py
examples/input_loop.py
funcmap/__init__.py
funcmap/mapper.py
funcmap-1.0.3.dist-info/DESCRIPTION.rst
funcmap-1.0.3.dist-info/METADATA
funcmap-1.0.3.dist-info/RECORD
funcmap-1.0.3.dist-info/WHEEL
funcmap-1.0.3.dist-info/metadata.json
funcmap-1.0.3.dist-info/top_level.txt
tests/__init__.py
tests/test_funcmapper.py
