Metadata-Version: 2.0
Name: funcmap
Version: 1.0.3
Summary: A small Python module to provide convenient mapping between Python functions and text input
Home-page: https://github.com/AKuederle/funcmap
Author: Arne Küderle
Author-email: a.kuederle@gmail.com
License: LICENSE.txt
Platform: UNKNOWN
Classifier: Programming Language :: Python :: 3
Classifier: Programming Language :: Python :: 3.4
Classifier: Programming Language :: Python :: 3.5
